claml2transmart/__init__.py
claml2transmart/__version__.py
claml2transmart/claml2transmart.py
claml2transmart/ontology_mapper.py
claml2transmart/ontology_writer.py
claml2transmart-0.1.5.dist-info/LICENSE
claml2transmart-0.1.5.dist-info/METADATA
claml2transmart-0.1.5.dist-info/WHEEL
claml2transmart-0.1.5.dist-info/entry_points.txt
claml2transmart-0.1.5.dist-info/top_level.txt
claml2transmart-0.1.5.dist-info/RECORD
